revised_stopwords/__init__.py
revised_stopwords/stopwords.py
revised_stopwords-0.1.4.dist-info/LICENSE
revised_stopwords-0.1.4.dist-info/METADATA
revised_stopwords-0.1.4.dist-info/WHEEL
revised_stopwords-0.1.4.dist-info/top_level.txt
revised_stopwords-0.1.4.dist-info/RECORD
