Metadata-Version: 2.2
Name: revised-stopwords
Version: 0.1.4
Summary: An optimized stopwords list for sentiment analysis that retains key negations like 'not', 'won't', and 'wouldn't', along with intensity modifiers like 'very' and 'most' to preserve sentiment accuracy.
Home-page: https://github.com/priyaa279/revised_stopwords
Author: Priyaa Gopal Shankar
Author-email: priyaashankar9498@gmail.com
Classifier: Programming Language :: Python :: 3
Classifier: License :: OSI Approved :: MIT License
Classifier: Operating System :: OS Independent
Requires-Python: >=3.6
License-File: LICENSE
Requires-Dist: nltk
Dynamic: author
Dynamic: author-email
Dynamic: classifier
Dynamic: description
Dynamic: description-content-type
Dynamic: home-page
Dynamic: requires-dist
Dynamic: requires-python
Dynamic: summary
